lua_auto_doc/Config_LuaAutoDoc.json
lua_auto_doc/__init__.py
lua_auto_doc/lua_auto_doc.py
lua_auto_doc/Assets/BuyMeACoffee.svg
lua_auto_doc/Assets/DarkModeButton.svg
lua_auto_doc/Assets/Deprecated.svg
lua_auto_doc/Assets/Discord.svg
lua_auto_doc/Assets/FolderClosed.svg
lua_auto_doc/Assets/FolderOpen.svg
lua_auto_doc/Assets/GitHub.svg
lua_auto_doc/Assets/GitLab.svg
lua_auto_doc/Assets/Internal.svg
lua_auto_doc/Assets/JetBrainsMono fonts LICENSE.txt
lua_auto_doc/Assets/JetBrainsMono-VariableFont_wght.ttf
lua_auto_doc/Assets/LightModeButton.svg
lua_auto_doc/Assets/LuaFile.svg
lua_auto_doc/Assets/LuaFileLight.svg
lua_auto_doc/Assets/Patreon.svg
lua_auto_doc/Assets/PayPal.svg
lua_auto_doc/Assets/RobotoSlab font LICENSE.txt
lua_auto_doc/Assets/RobotoSlab-VariableFont_wght.ttf
lua_auto_doc/Assets/Twitter.svg
lua_auto_doc/Favicon/android-chrome-192x192.png
lua_auto_doc/Favicon/android-chrome-512x512.png
lua_auto_doc/Favicon/apple-touch-icon.png
lua_auto_doc/Favicon/browserconfig.xml
lua_auto_doc/Favicon/favicon-16x16.png
lua_auto_doc/Favicon/favicon-32x32.png
lua_auto_doc/Favicon/mstile-150x150.png
lua_auto_doc/Favicon/safari-pinned-tab.svg
lua_auto_doc/Favicon/site.webmanifest
lua_auto_doc/HTMLFragments/code_objects/CO_TemplateFifthLayer.html
lua_auto_doc/HTMLFragments/code_objects/CO_TemplateFourthLayer.html
lua_auto_doc/HTMLFragments/code_objects/CO_TemplateSecondLayer.html
lua_auto_doc/HTMLFragments/code_objects/CO_TemplateSixthLayer.html
lua_auto_doc/HTMLFragments/code_objects/CO_TemplateThirdLayer.html
lua_auto_doc/HTMLFragments/code_objects/CodeObject.html
lua_auto_doc/HTMLFragments/extra/EX_TemplateFourthLayer.html
lua_auto_doc/HTMLFragments/extra/EX_TemplateSecondLayer.html
lua_auto_doc/HTMLFragments/extra/EX_TemplateThirdLayer.html
lua_auto_doc/HTMLFragments/extra/decorators.html
lua_auto_doc/HTMLFragments/main_page/index.html
lua_auto_doc/HTMLFragments/search_page/search_page.html
lua_auto_doc/HTMLFragments/source_code_mirror/SCFM_TemplateSecondLayer.html
LuaAutoDoc-0.9.1.dist-info/LICENSE
LuaAutoDoc-0.9.1.dist-info/METADATA
LuaAutoDoc-0.9.1.dist-info/WHEEL
LuaAutoDoc-0.9.1.dist-info/entry_points.txt
LuaAutoDoc-0.9.1.dist-info/top_level.txt
LuaAutoDoc-0.9.1.dist-info/RECORD
