Metadata-Version: 2.1
Name: LuaAutoDoc
Version: 0.9.1
Summary: Generates full HTML documentation of a Lua project with LuaDoc tags.
Home-page: https://gitlab.com/UlrikHD/LuaAutoDoc
Author: Ulrik Holtgaard Digerud
Author-email: githubuhd@runbox.com
License: MIT License
Project-URL: Bug Tracker, https://gitlab.com/UlrikHD/LuaAutoDoc/-/issues
Keywords: Lua,documentation,LuaDoc,HTML,LuaAutoDoc,autodoc,auto documentation,Lua documentation
Platform: UNKNOWN
Classifier: Development Status :: 4 - Beta
Classifier: Intended Audience :: Developers
Classifier: License :: OSI Approved :: MIT License
Classifier: Natural Language :: English
Classifier: Operating System :: OS Independent
Classifier: Programming Language :: Python :: 3 :: Only
Classifier: Programming Language :: Python :: 3.10
Classifier: Programming Language :: Python :: 3.11
Classifier: Programming Language :: Python :: 3.12
Classifier: Topic :: Documentation
Classifier: Topic :: Software Development :: Documentation
Classifier: Typing :: Typed
Requires-Python: >=3.10
License-File: LICENSE
